skill_avmusic/LICENSE.md
skill_avmusic/README.md
skill_avmusic/__init__.py
skill_avmusic/skill.json
skill_avmusic/version.py
skill_avmusic/version_bump.py
skill_avmusic/dialog/de-de/ChangeMind.dialog
skill_avmusic/dialog/de-de/PlayNow.dialog
skill_avmusic/dialog/de-de/SayResume.dialog
skill_avmusic/dialog/de-de/SayStop.dialog
skill_avmusic/dialog/de-de/TryAgain.dialog
skill_avmusic/dialog/en-us/ChangeMind.dialog
skill_avmusic/dialog/en-us/PlayNow.dialog
skill_avmusic/dialog/en-us/SayResume.dialog
skill_avmusic/dialog/en-us/SayStop.dialog
skill_avmusic/dialog/en-us/TryAgain.dialog
skill_avmusic/neon_skill_avmusic.egg-info/PKG-INFO
skill_avmusic/neon_skill_avmusic.egg-info/SOURCES.txt
skill_avmusic/neon_skill_avmusic.egg-info/dependency_links.txt
skill_avmusic/neon_skill_avmusic.egg-info/entry_points.txt
skill_avmusic/neon_skill_avmusic.egg-info/requires.txt
skill_avmusic/neon_skill_avmusic.egg-info/top_level.txt
skill_avmusic/ui/Video.qml
skill_avmusic/ui/qmldir
skill_avmusic/vocab/de-de/AVmusicKeyword.voc
skill_avmusic/vocab/de-de/AgreementKeyword.voc
skill_avmusic/vocab/de-de/DeclineKeyword.voc
skill_avmusic/vocab/en-us/AVmusicKeyword.voc
skill_avmusic/vocab/en-us/AgreementKeyword.voc
skill_avmusic/vocab/en-us/DeclineKeyword.voc
skill_avmusic/vocab/en-us/Mix.voc
skill_avmusic/vocab/en-us/Neon.voc
skill_avmusic/vocab/en-us/Playback.voc
skill_avmusic/vocab/en-us/Repeat.voc
skill_avmusic/vocab/en-us/Video.voc
neon_skill_avmusic-0.1.0.dist-info/LICENSE.md
neon_skill_avmusic-0.1.0.dist-info/METADATA
neon_skill_avmusic-0.1.0.dist-info/WHEEL
neon_skill_avmusic-0.1.0.dist-info/entry_points.txt
neon_skill_avmusic-0.1.0.dist-info/top_level.txt
neon_skill_avmusic-0.1.0.dist-info/RECORD
