Metadata-Version: 2.1
Name: neon-skill-avmusic
Version: 0.1.0
Summary: UNKNOWN
Home-page: https://github.com/NeonGeckoCom/skill-avmusic
Author: Neongecko
Author-email: developers@neon.ai
License: BSD-3-Clause
Platform: UNKNOWN
Requires-Dist: youtube-dl (>=2021.5.16)
Requires-Dist: pafy (~=0.5.5)
Requires-Dist: youtube-searcher
Requires-Dist: neon-utils (<2.0.0,>=0.5.7)
